{
  "id": "question-1",
  "questionText": "An animal cell contains:",
  "answers": [
    {
      "id": "answer-1",
      "options": [
        { "id": "opt-1", "optionText": "Cell Wall", "isCorrect": false },
        { "id": "opt-2", "optionText": "Ribosomes", "isCorrect": true }
      ]
    },
    {
      "id": "answer-2",
      "options": [
        { "id": "opt-1", "optionText": "Cytoplasm", "isCorrect": true },
        { "id": "opt-2", "optionText": "Chloroplast", "isCorrect": false }
      ]
    },
    {
      "id": "answer-3",
      "options": [
        { "id": "opt-1", "optionText": "Partially permeable membrane", "isCorrect": true },
        { "id": "opt-2", "optionText": "Impermeable membrane", "isCorrect": false }
      ]
    },
    {
      "id": "answer-4",
      "options": [
        { "id": "opt-1", "optionText": "Cellulose", "isCorrect": false },
        { "id": "opt-2", "optionText": "Mitochondria", "isCorrect": true }
      ]
    }
  ]
}